proget/__init__.py
Proget-2.6.dist-info/LICENSE
Proget-2.6.dist-info/METADATA
Proget-2.6.dist-info/WHEEL
Proget-2.6.dist-info/entry_points.txt
Proget-2.6.dist-info/top_level.txt
Proget-2.6.dist-info/RECORD
