Metadata-Version: 2.1
Name: Proget
Version: 2.6
Summary: A software download tool
Home-page: https://github.com/Whirlpool-Programmer/Proget
Author: Whirlpool-Programmer
Author-email: whirlpool.programmer@outlook.com
License: MIT License
Platform: UNKNOWN
Classifier: Programming Language :: Python :: 3
Classifier: License :: OSI Approved :: MIT License
Classifier: Operating System :: OS Independent
Requires: pyyaml
Requires: urllib3
Requires: requests
Requires: alive_progress
License-File: LICENSE
Requires-Dist: pyyaml
Requires-Dist: urllib3
Requires-Dist: requests
Requires-Dist: alive-progress
